marduk.py
marduk-0.0.0a1.dist-info/DESCRIPTION.rst
marduk-0.0.0a1.dist-info/METADATA
marduk-0.0.0a1.dist-info/RECORD
marduk-0.0.0a1.dist-info/WHEEL
marduk-0.0.0a1.dist-info/metadata.json
marduk-0.0.0a1.dist-info/top_level.txt
marduk-0.0.0a1.dist-info/zip-safe
